odoo8_addon_l10n_it_fiscal_document_type-8.0.2.0.0-nspkg.pth
odoo_addons/l10n_it_fiscal_document_type/README.rst
odoo_addons/l10n_it_fiscal_document_type/__init__.py
odoo_addons/l10n_it_fiscal_document_type/__openerp__.py
odoo_addons/l10n_it_fiscal_document_type/data/fiscal.document.type.csv
odoo_addons/l10n_it_fiscal_document_type/i18n/it.po
odoo_addons/l10n_it_fiscal_document_type/i18n/l10n_it_fiscal_document_type.pot
odoo_addons/l10n_it_fiscal_document_type/i18n/sl.po
odoo_addons/l10n_it_fiscal_document_type/models/__init__.py
odoo_addons/l10n_it_fiscal_document_type/models/account_fiscal_position.py
odoo_addons/l10n_it_fiscal_document_type/models/account_invoice.py
odoo_addons/l10n_it_fiscal_document_type/models/fiscal_document_type.py
odoo_addons/l10n_it_fiscal_document_type/models/journal.py
odoo_addons/l10n_it_fiscal_document_type/models/res_partner.py
odoo_addons/l10n_it_fiscal_document_type/readme/CONFIGURE.rst
odoo_addons/l10n_it_fiscal_document_type/readme/CONTRIBUTORS.rst
odoo_addons/l10n_it_fiscal_document_type/readme/CREDITS.rst
odoo_addons/l10n_it_fiscal_document_type/readme/DESCRIPTION.rst
odoo_addons/l10n_it_fiscal_document_type/security/ir.model.access.csv
odoo_addons/l10n_it_fiscal_document_type/static/description/icon.png
odoo_addons/l10n_it_fiscal_document_type/static/description/index.html
odoo_addons/l10n_it_fiscal_document_type/tests/__init__.py
odoo_addons/l10n_it_fiscal_document_type/tests/test_doc_type.py
odoo_addons/l10n_it_fiscal_document_type/views/account_invoice_view.xml
odoo_addons/l10n_it_fiscal_document_type/views/account_view.xml
odoo_addons/l10n_it_fiscal_document_type/views/fiscal_document_type_view.xml
odoo_addons/l10n_it_fiscal_document_type/views/res_partner_view.xml
odoo8_addon_l10n_it_fiscal_document_type-8.0.2.0.0.dist-info/METADATA
odoo8_addon_l10n_it_fiscal_document_type-8.0.2.0.0.dist-info/WHEEL
odoo8_addon_l10n_it_fiscal_document_type-8.0.2.0.0.dist-info/namespace_packages.txt
odoo8_addon_l10n_it_fiscal_document_type-8.0.2.0.0.dist-info/top_level.txt
odoo8_addon_l10n_it_fiscal_document_type-8.0.2.0.0.dist-info/RECORD
