Metadata-Version: 2.1
Name: odoo8-addon-l10n-it-fiscal-document-type
Version: 8.0.2.0.0
Summary: Italian Localization - Tipi di documento fiscale per dichiarativi
Home-page: https://github.com/OCA/l10n-italy/tree/8.0/l10n_it_fiscal_document_type
Author: Link It srl, Odoo Community Association (OCA)
Author-email: support@odoo-community.org
License: LGPL-3
Platform: UNKNOWN
Classifier: Programming Language :: Python
Classifier: Framework :: Odoo
Classifier: License :: OSI Approved :: GNU Lesser General Public License v3 (LGPLv3)
Requires-Python: ~=2.7
Requires-Dist: odoo8-addon-l10n-it-account
Requires-Dist: odoo (<9.0a,>=8.0a)
